<odoo>
<!--    <template id="error_popup_template" inherit_id="web.dialog_error">-->
<!--        <xpath expr="//div[@class='modal-content']" position="inside">-->
<!--            <div class="modal-header">-->
<!--                <h4 class="modal-title">Error</h4>-->
<!--            </div>-->
<!--            <div class="modal-body">-->
<!--                <p t-if="error_msg" t-esc="error_msg"/>-->
<!--            </div>-->
<!--            <div class="modal-footer">-->
<!--                <button type="button" class="btn btn-primary" data-dismiss="modal">Close</button>-->
<!--            </div>-->
<!--        </xpath>-->
<!--    </template>-->
</odoo>